{
    "version": "0.2",
    "ignorePaths": [],
    "dictionaryDefinitions": [],
    "dictionaries": [],
    "words": [
        "abrir",
        "acceso",
        "acelera",
        "aceptadas",
        "actualizaciones",
        "administración",
        "Administración",
        "adoptar",
        "Agregar",
        "Aislar",
        "ajuste",
        "Alcance",
        "alinea",
        "Alinear",
        "alternativas",
        "apareció",
        "aprendidas",
        "aprendizaje",
        "apuntar",
        "arquitectónico",
        "aunque",
        "avanzada",
        "avanzar",
        "bien",
        "binarios",
        "bloque",
        "bloqueos",
        "busca",
        "Cada",
        "Cambiar",
        "capas",
        "caracteres",
        "Causa",
        "cerrado",
        "Cerrar",
        "coherencia",
        "coherente",
        "comandos",
        "comentarios",
        "Comentarios",
        "Compatibilidad",
        "complejidad",
        "completamente",
        "Componentes",
        "común",
        "conceptos",
        "conceptualmente",
        "conectividad",
        "configurado",
        "Confirmación",
        "confusión",
        "conocimiento",
        "constituye",
        "construirán",
        "Continuar",
        "controlada",
        "controlado",
        "corporativa",
        "corporativos",
        "crear",
        "creás",
        "creaste",
        "críticos",
        "cuál",
        "cumple",
        "darlo",
        "debe",
        "debido",
        "decidió",
        "Decime",
        "decisión",
        "definido",
        "dejás",
        "dentro",
        "dependencia",
        "descargas",
        "desde",
        "después",
        "Después",
        "detecta",
        "detectar",
        "diagrama",
        "diagramas",
        "Diferencias",
        "directamente",
        "directorio",
        "diseñada",
        "documentada",
        "Documentar",
        "documentará",
        "Documentarlo",
        "donde",
        "eclusivo",
        "Editar",
        "educativos",
        "Ejemplo",
        "elegido",
        "enlazá",
        "entendible",
        "equivalente",
        "equivalentes",
        "errores",
        "escala",
        "escalabilidad",
        "escenario",
        "Espacios",
        "esperado",
        "estaba",
        "estable",
        "estas",
        "estáticos",
        "esté",
        "Esto",
        "evitar",
        "evolucionar",
        "evolutivo",
        "exclusivo",
        "explicación",
        "exponer",
        "exposición",
        "Extensión",
        "externa",
        "Facilidad",
        "facilita",
        "Facilitar",
        "fácilmente",
        "fallaba",
        "fase",
        "física",
        "físico",
        "frente",
        "fuera",
        "funcionaron",
        "futura",
        "futuras",
        "futuros",
        "generando",
        "habilita",
        "habituales",
        "hypervisores",
        "incidente",
        "incluido",
        "incompatibilidades",
        "inicial",
        "instalación",
        "instalado",
        "integrarse",
        "interfaz",
        "interna",
        "internamente",
        "Introducción",
        "Justificación",
        "Lecciones",
        "Limitaciones",
        "lógico",
        "lugar",
        "mantener",
        "manteniendo",
        "mantenimiento",
        "manualmente",
        "máquina",
        "Máquinas",
        "mencionás",
        "Menor",
        "menos",
        "Menos",
        "Mientras",
        "mínima",
        "mismo",
        "modelo",
        "Mostrando",
        "Motivos",
        "muchísimo",
        "necesita",
        "nueva",
        "ocurrió",
        "opcional",
        "opciones",
        "operación",
        "operativa",
        "operativo",
        "orientado",
        "parseo",
        "partir",
        "pasamos",
        "pasar",
        "pensada",
        "pequeña",
        "permite",
        "Permite",
        "permitir",
        "podés",
        "porque",
        "preferís",
        "Preparación",
        "Preparar",
        "presentadó",
        "previa",
        "prioriza",
        "priorizando",
        "Probar",
        "producción",
        "productiva",
        "progresivamente",
        "Provee",
        "provocó",
        "proyección",
        "pudiera",
        "pudo",
        "puede",
        "punto",
        "raíz",
        "rápida",
        "realista",
        "realiza",
        "rediseñar",
        "reducir",
        "referencia",
        "referenciar",
        "Relación",
        "renderizaba",
        "renderizar",
        "Rendimiento",
        "representa",
        "reproducibilidad",
        "requieren",
        "responsabilidades",
        "Resultado",
        "riesgos",
        "sección",
        "seguridad",
        "Separar",
        "Seperara",
        "servicio",
        "Servidor",
        "sesión",
        "siempre",
        "Siguiente",
        "simula",
        "Simular",
        "sino",
        "sintaxis",
        "sirviendo",
        "Sobre",
        "soportados",
        "también",
        "texto",
        "tipo",
        "Transferencia",
        "único",
        "utiliza",
        "utilizadas",
        "utilizar",
        "válida",
        "validado",
        "validarse",
        "vboxnet",
        "Verificación",
        "verificar",
        "Verificar",
        "versionada",
        "versionado",
        "versionados",
        "Visión",
        "VNETs",
        "volver",
        "volvés"
    ],
    "ignoreWords": [],
    "import": []
}
